humancompatible/__init__.py
humancompatible/detect/__init__.py
humancompatible/detect/detect_bias.py
humancompatible/detect/evaluate_bias.py
humancompatible/detect/binarizer/Binarizer.py
humancompatible/detect/binarizer/__init__.py
humancompatible/detect/data_handler/DataHandler.py
humancompatible/detect/data_handler/__init__.py
humancompatible/detect/data_handler/types.py
humancompatible/detect/data_handler/features/Binary.py
humancompatible/detect/data_handler/features/Categorical.py
humancompatible/detect/data_handler/features/Contiguous.py
humancompatible/detect/data_handler/features/Feature.py
humancompatible/detect/data_handler/features/Mixed.py
humancompatible/detect/data_handler/features/__init__.py
humancompatible/detect/data_handler/features/utils.py
humancompatible/detect/helpers/__init__.py
humancompatible/detect/helpers/prepare.py
humancompatible/detect/helpers/utils.py
humancompatible/detect/methods/__init__.py
humancompatible/detect/methods/l_inf/__init__.py
humancompatible/detect/methods/l_inf/l_inf.py
humancompatible/detect/methods/l_inf/lp_tools.py
humancompatible/detect/methods/msd/__init__.py
humancompatible/detect/methods/msd/mapping_msd.py
humancompatible/detect/methods/msd/metrics_msd.py
humancompatible/detect/methods/msd/msd.py
humancompatible/detect/methods/msd/one_rule.py
humancompatible_detect-0.1.4.dist-info/licenses/LICENSE
humancompatible_detect-0.1.4.dist-info/METADATA
humancompatible_detect-0.1.4.dist-info/WHEEL
humancompatible_detect-0.1.4.dist-info/top_level.txt
humancompatible_detect-0.1.4.dist-info/RECORD
