Metadata-Version: 2.4
Name: humancompatible-detect
Version: 0.1.4
Summary: A Python Toolkit for Detecting Bias in AI Models
Author: Germán Martínez Matilla, Illia Kryvoviaz, Jakub Mareček, Jiří Němeček
Maintainer-email: Illia Kryvoviaz <illiakryvoviaz@gmail.com>, Jiří Němeček <nemecj38@fel.cvut.cz>
License-Expression: Apache-2.0
Project-URL: Homepage, https://github.com/humancompatible/detect
Project-URL: Documentation, https://humancompatible-detect.readthedocs.io/en/latest
Project-URL: Issues, https://github.com/humancompatible/detect/issues
Keywords: toolkit,fairness,bias,ai,ml,subgroup,intersectional,msd,linf,optimization,milp,pyomo,highs,gurobi
Classifier: Development Status :: 3 - Alpha
Classifier: Intended Audience :: Science/Research
Classifier: Intended Audience :: Developers
Classifier: Operating System :: OS Independent
Classifier: Programming Language :: Python
Classifier: Programming Language :: Python :: 3
Classifier: Programming Language :: Python :: 3 :: Only
Classifier: Programming Language :: Python :: 3.10
Classifier: Programming Language :: Python :: 3.11
Classifier: Programming Language :: Python :: 3.12
Classifier: Programming Language :: Python :: 3.13
Classifier: Topic :: Scientific/Engineering
Classifier: Topic :: Scientific/Engineering :: Artificial Intelligence
Classifier: Topic :: Scientific/Engineering :: Information Analysis
Classifier: Topic :: Scientific/Engineering :: Mathematics
Classifier: Topic :: Software Development :: Libraries :: Python Modules
Requires-Python: >=3.10
License-File: LICENSE
Requires-Dist: numpy<3.0,>=2.2
Requires-Dist: pandas<3.0,>=2.2
Requires-Dist: pyomo<7.0,>=6.9
Requires-Dist: highspy<2.0,>=1.10
Requires-Dist: scipy<2.0,>=1.16
Requires-Dist: tqdm<5.0,>=4.6
Provides-Extra: gurobi
Requires-Dist: gurobipy<13.0,>=12.0; extra == "gurobi"
Provides-Extra: cplex
Requires-Dist: cplex<23.0,>=22.1.2.0; extra == "cplex"
Provides-Extra: xpress
Requires-Dist: xpress<10.0,>=9.8.0; extra == "xpress"
Provides-Extra: examples
Requires-Dist: jupyterlab<5.0,>=4.2; extra == "examples"
Requires-Dist: matplotlib<4.0,>=3.10; extra == "examples"
Requires-Dist: folktables<0.1,>=0.0.12; extra == "examples"
Provides-Extra: docs
Requires-Dist: sphinx<8.0,>=7.0; extra == "docs"
Requires-Dist: myst-parser<4.0,>=3.0; extra == "docs"
Requires-Dist: sphinx-rtd-theme<3.0,>=2.0; extra == "docs"
Provides-Extra: dev
Requires-Dist: pytest<9.0,>=8.0; extra == "dev"
Requires-Dist: ruff<0.7,>=0.6; extra == "dev"
Requires-Dist: black<25.0,>=24.8; extra == "dev"
Requires-Dist: build<2.0,>=1.2; extra == "dev"
Requires-Dist: twine<6.0,>=5.0; extra == "dev"
Dynamic: license-file
